[
	{
		"name": "Ecodry 74N01"
	},
	{
		"name": "Ecodry 75N11"
	},
	{
		"name": "Ecodry 76B01"
	},
	{
		"name": "Ecodry 76B02"
	},
	{
		"name": "Ecodry 76B03"
	},
	{
		"name": "Ecodry 76B05"
	},
	{
		"name": "Ecodry 87N52"
	},
	{
		"name": "ECOFIB-Leisten zum schutz - emballé"
	},
	{
		"name": "Ecofill 22B14 I"
	},
	{
		"name": "Ecofill 23B71"
	},
	{
		"name": "Ecofill 23B81"
	},
	{
		"name": "Ecofill 23S90"
	},
	{
		"name": "Ecofill 25B81"
	},
	{
		"name": "Ecofill 25B82Al"
	},
	{
		"name": "Ecofill 25B83 Al"
	},
	{
		"name": "Ecofill 28S86"
	},
	{
		"name": "Ecofill 46B80"
	},
	{
		"name": "Ecoflow 33B81 FS"
	},
	{
		"name": "Ecoflow 33B82 FS"
	},
	{
		"name": "Ecoflow 33B82 FSFM"
	},
	{
		"name": "Ecoflow 34B80 APF"
	},
	{
		"name": "Ecoflow 34B80 FS"
	},
	{
		"name": "Ecoflow 34B80 FSFM"
	},
	{
		"name": "Ecoflow 38S83"
	},
	{
		"name": "Ecoflow 38S86"
	},
	{
		"name": "Ecoflow 38S86 AL"
	},
	{
		"name": "Ecoflow 46B83"
	},
	{
		"name": "Ecoflow 53B81"
	},
	{
		"name": "Ecoflow 54B82"
	},
	{
		"name": "Ecoflow 54B82 FSFM"
	},
	{
		"name": "Ecoflow 54B83"
	},
	{
		"name": "Ecoflow 54B85Al FS"
	},
	{
		"name": "Ecoflow 59S80"
	},
	{
		"name": "Ecoflow 59S80 FSFM"
	},
	{
		"name": "Ecoflow 65N80"
	},
	{
		"name": "Ecoflow 73B82 SR FS"
	},
	{
		"name": "Ecogrout 050 RN"
	},
	{
		"name": "Ecogrout 050RN AT3"
	},
	{
		"name": "Ecogrout 110 RN"
	},
	{
		"name": "Ecogrout 110RN AT3"
	},
	{
		"name": "Ecogrout 620RN AT3"
	},
	{
		"name": "Ecogrout 621RN AT3"
	},
	{
		"name": "Ecogrout 650 RN"
	},
	{
		"name": "Ecogrout 650RN MIX At3"
	},
	{
		"name": "Ecojet 14B01"
	},
	{
		"name": "Ecojet 14N51"
	},
	{
		"name": "Ecojet 16B60"
	},
	{
		"name": "Ecojet 16N01"
	},
	{
		"name": "Ecojet 16N01 FS"
	},
	{
		"name": "Ecojet 22B03"
	},
	{
		"name": "Ecojet 22B13 I"
	},
	{
		"name": "Ecojet 23B01"
	},
	{
		"name": "Ecojet 23B03"
	},
	{
		"name": "Ecojet 23B03 Al"
	},
	{
		"name": "Ecojet 23B03 Fonderie"
	},
	{
		"name": "Ecojet 23B05 fonderie"
	},
	{
		"name": "Ecojet 23B06"
	},
	{
		"name": "Ecojet 24B03/1"
	},
	{
		"name": "Ecojet 32B04 GD"
	},
	{
		"name": "Ecojet 34N03"
	},
	{
		"name": "Ecojet 34N06"
	},
	{
		"name": "Ecojet 38S60"
	},
	{
		"name": "Ecojet 54B01 GD"
	},
	{
		"name": "Ecojet 54N01 GD"
	},
	{
		"name": "Ecojet 95N01"
	},
	{
		"name": "Ecokast 20B12 I"
	},
	{
		"name": "Ecokast 22B01"
	},
	{
		"name": "Ecokast 22B02"
	},
	{
		"name": "Ecokast 22B51 I"
	},
	{
		"name": "Ecokast 23B02"
	},
	{
		"name": "Ecokast 24B02"
	},
	{
		"name": "Ecokast 26B01"
	},
	{
		"name": "Ecokast 26B01 FS"
	},
	{
		"name": "Ecokast 26B03"
	},
	{
		"name": "Ecokast 26B03 FS"
	},
	{
		"name": "Ecokast 32B01"
	},
	{
		"name": "Ecokast 32B01 FS"
	},
	{
		"name": "Ecokast 32B01 FSFM"
	},
	{
		"name": "Ecokast 32B02 FS"
	},
	{
		"name": "Ecokast 32B50 FSFM"
	},
	{
		"name": "Ecokast 33B01 FS"
	},
	{
		"name": "Ecokast 33B01 FSFM"
	},
	{
		"name": "Ecokast 33B02"
	},
	{
		"name": "Ecokast 33B02 FS"
	},
	{
		"name": "Ecokast 33B02 FSFM"
	},
	{
		"name": "Ecokast 33N01 FS"
	},
	{
		"name": "Ecokast 33S01 FS"
	},
	{
		"name": "Ecokast 33S02 FS"
	},
	{
		"name": "Ecokast 33S02 FSFM"
	},
	{
		"name": "Ecokast 34B01 FS"
	},
	{
		"name": "Ecokast 34B01 FSFM"
	},
	{
		"name": "Ecokast 34B04"
	},
	{
		"name": "Ecokast 34B04 FS"
	},
	{
		"name": "Ecokast 34B05 FS"
	},
	{
		"name": "Ecokast 36B01 FS"
	},
	{
		"name": "Ecokast 36B01 FSFM"
	},
	{
		"name": "Ecokast 36B03"
	},
	{
		"name": "Ecokast 36B10 FS"
	},
	{
		"name": "Ecokast 39S01"
	},
	{
		"name": "Ecokast 46B01"
	},
	{
		"name": "Ecokast 46B01 FM"
	},
	{
		"name": "Ecokast 46B71"
	},
	{
		"name": "Ecokast 51B01"
	},
	{
		"name": "Ecokast 53B03 FS"
	},
	{
		"name": "Ecokast 53B40 FS"
	},
	{
		"name": "Ecokast 53B48 FS"
	},
	{
		"name": "Ecokast 53B48 FSFM"
	},
	{
		"name": "Ecokast 53B50 FS"
	},
	{
		"name": "Ecokast 53B50 FSFM"
	},
	{
		"name": "Ecokast 53B90 Al FS"
	},
	{
		"name": "Ecokast 53B91 Al FS"
	},
	{
		"name": "Ecokast 54B01 FS"
	},
	{
		"name": "Ecokast 54B40 FS"
	},
	{
		"name": "Ecokast 54B41 FS"
	},
	{
		"name": "Ecokast 54B45 FS"
	},
	{
		"name": "Ecokast 54B45 FSFM"
	},
	{
		"name": "Ecokast 54B48 FS"
	},
	{
		"name": "Ecokast 54B48 FS sacs"
	},
	{
		"name": "Ecokast 54B48 FSFM"
	},
	{
		"name": "ECOKAST 54B49 FS"
	},
	{
		"name": "Ecokast 54B49 FSFM"
	},
	{
		"name": "Ecokast 54B60 Al FS"
	},
	{
		"name": "Ecokast 54B60 Al FSFM"
	},
	{
		"name": "Ecokast 54N02"
	},
	{
		"name": "Ecokast 54N02 FM"
	},
	{
		"name": "Ecokast 54N03"
	},
	{
		"name": "Ecokast 54N03 FM"
	},
	{
		"name": "Ecokast 54N05"
	},
	{
		"name": "Ecokast 54N10"
	},
	{
		"name": "Ecokast 54N13"
	},
	{
		"name": "Ecokast 54N15"
	},
	{
		"name": "Ecokast 54N17"
	},
	{
		"name": "Ecokast 54N17 FM"
	},
	{
		"name": "Ecokast 54N17 NLMK"
	},
	{
		"name": "Ecokast 54N18"
	},
	{
		"name": "Ecokast 54S20 FM"
	},
	{
		"name": "Ecokast 55B50 FSFM"
	},
	{
		"name": "Ecokast 55B50FS"
	},
	{
		"name": "Ecokast 55N06"
	},
	{
		"name": "Ecokast 55N06 G.10"
	},
	{
		"name": "Ecokast 55N06 SAC"
	},
	{
		"name": "Ecokast 55N06 SiC R"
	},
	{
		"name": "Ecokast 55N18"
	},
	{
		"name": "Ecokast 55N19"
	},
	{
		"name": "Ecokast 55N25"
	},
	{
		"name": "Ecokast 55N34"
	},
	{
		"name": "Ecokast 55N35"
	},
	{
		"name": "Ecokast 55N43"
	},
	{
		"name": "Ecokast 55N46"
	},
	{
		"name": "Ecokast 55N46 sacs"
	},
	{
		"name": "Ecokast 55N61 B"
	},
	{
		"name": "Ecokast 55N61 FS"
	},
	{
		"name": "ECOKAST 55N61 SC/SB"
	},
	{
		"name": "Ecokast 55N63"
	},
	{
		"name": "Ecokast 55N63 B"
	},
	{
		"name": "Ecokast 55N63 S"
	},
	{
		"name": "Ecokast 55N70"
	},
	{
		"name": "Ecokast 55S02"
	},
	{
		"name": "Ecokast 55S02 A2"
	},
	{
		"name": "Ecokast 55S02 A2 FM"
	},
	{
		"name": "Ecokast 55S02 FM"
	},
	{
		"name": "Ecokast 55S03"
	},
	{
		"name": "Ecokast 55S03 FM"
	},
	{
		"name": "Ecokast 55S06"
	},
	{
		"name": "Ecokast 55S06 FM"
	},
	{
		"name": "Ecokast 56N09"
	},
	{
		"name": "Ecokast 56N61"
	},
	{
		"name": "Ecokast 58N02"
	},
	{
		"name": "Ecokast 58N02 FM"
	},
	{
		"name": "Ecokast 58N10S"
	},
	{
		"name": "Ecokast 58N10S FM"
	},
	{
		"name": "Ecokast 58N32"
	},
	{
		"name": "Ecokast 58N33"
	},
	{
		"name": "Ecokast 59S01FS"
	},
	{
		"name": "Ecokast 75N06 SR"
	},
	{
		"name": "Ecokast 75N61 SR"
	},
	{
		"name": "Ecoplac N"
	},
	{
		"name": "Ecoram 11B02"
	},
	{
		"name": "Ecoram 11B03"
	},
	{
		"name": "Ecoram 11B04"
	},
	{
		"name": "Ecoram 14B03"
	},
	{
		"name": "Ecoram 14B03 Poudre"
	},
	{
		"name": "Ecoram 14N54"
	},
	{
		"name": "Ecoram 76B80"
	},
	{
		"name": "Ecoram 76B80 Poudre"
	},
	{
		"name": "Ecoram 94B01"
	},
	{
		"name": "Ecoram 94B05"
	},
	{
		"name": "Ecoram 94B50P"
	},
	{
		"name": "Ecoram 94N03"
	},
	{
		"name": "Ecoram 94N11"
	},
	{
		"name": "Ecoram 94N11P"
	},
	{
		"name": "Ecoram 94N80"
	},
	{
		"name": "Ecoram 94N80 P"
	},
	{
		"name": "Ecoram 94N80 sac"
	},
	{
		"name": "Ecoram 95B60P"
	},
	{
		"name": "Ecoram 95N01 D"
	},
	{
		"name": "Ecoram 95N01P"
	},
	{
		"name": "Ecoram 95N02 P"
	},
	{
		"name": "Ecoset 10B01"
	},
	{
		"name": "Ecoset 11B10"
	},
	{
		"name": "Ecoset 14B02"
	},
	{
		"name": "Ecoset 14B19"
	},
	{
		"name": "Ecoset 14B20"
	},
	{
		"name": "Ecoset 16B50"
	},
	{
		"name": "Ecoset 16B51"
	},
	{
		"name": "Ecoset 17B50"
	},
	{
		"name": "Ecoset 17B51"
	},
	{
		"name": "Ecoset 19B20"
	},
	{
		"name": "Ecoset 19B21"
	},
	{
		"name": "Ecoset 23B04"
	},
	{
		"name": "Ecoset 25B01"
	},
	{
		"name": "Ecoset 55N01"
	},
	{
		"name": "Ecotap 111BS"
	},
	{
		"name": "Ecotap 111M"
	},
	{
		"name": "Ecotap 112MS"
	},
	{
		"name": "Ecotap 112W"
	},
	{
		"name": "Ecotap 113W"
	},
	{
		"name": "Ecotap 115W"
	},
	{
		"name": "Ecotap 117 MS"
	},
	{
		"name": "Ecotap 121BS"
	},
	{
		"name": "Ecotap 122BS"
	},
	{
		"name": "Ecotap 1502MS"
	},
	{
		"name": "Ecotap 1503MS"
	},
	{
		"name": "Ecotap 1504MS"
	},
	{
		"name": "Ecotap 1506 MF"
	},
	{
		"name": "Ecotap 1510 MS"
	},
	{
		"name": "Ecotap 1511BS"
	},
	{
		"name": "Ecotap 1606MF"
	},
	{
		"name": "Ecotap 1608MF"
	},
	{
		"name": "Ecotap 1609 MF"
	},
	{
		"name": "Ecotap 1610MF"
	},
	{
		"name": "Ecotap 1612MF"
	},
	{
		"name": "Ecotap 1626RS"
	},
	{
		"name": "Ecotap 1627RS"
	},
	{
		"name": "Ecotap 1628RS"
	},
	{
		"name": "Ecotap 2111R"
	},
	{
		"name": "Ecotap 211R 50-100"
	},
	{
		"name": "Ecotap 212MS"
	},
	{
		"name": "Ecotap 213 MS/2"
	},
	{
		"name": "Ecotap 213MS/2"
	},
	{
		"name": "Ecotap 214MS"
	},
	{
		"name": "Ecotap 226 MF"
	},
	{
		"name": "Ecotap 2262RF"
	},
	{
		"name": "Ecotap 226MF"
	},
	{
		"name": "Ecotap 228BF"
	},
	{
		"name": "Ecotap 230MS"
	},
	{
		"name": "Ecotap 232 M"
	},
	{
		"name": "Ecotap 232 MF"
	},
	{
		"name": "Ecotap 2321 MF"
	},
	{
		"name": "Ecotap 2321MF"
	},
	{
		"name": "Ecotap 2323MF"
	},
	{
		"name": "Ecotap 2325MS"
	},
	{
		"name": "Ecotap 2327 RS"
	},
	{
		"name": "Ecotap 232M"
	},
	{
		"name": "Ecotap 234MF"
	},
	{
		"name": "Ecotap 2360RF"
	},
	{
		"name": "Ecotap 2361RF"
	},
	{
		"name": "Ecotap 2363RF"
	},
	{
		"name": "Ecotap 2364RF"
	},
	{
		"name": "Ecotap 2365RF"
	},
	{
		"name": "Ecotap 237 MF"
	},
	{
		"name": "Ecotap 2378MF"
	},
	{
		"name": "Ecotap 243M/1"
	},
	{
		"name": "Ecotap 247 MF"
	},
	{
		"name": "Ecotap 2471MF"
	},
	{
		"name": "Ecotap 2474MF"
	},
	{
		"name": "Ecotap 2478 MF"
	},
	{
		"name": "Ecotap 2478MF"
	},
	{
		"name": "Ecotap 247MF"
	},
	{
		"name": "Ecotap 248 MS"
	},
	{
		"name": "Ecotap 2500 MF"
	},
	{
		"name": "Ecotap 2500MF"
	},
	{
		"name": "Ecotap 2502MF"
	},
	{
		"name": "Ecotap 2503MF"
	},
	{
		"name": "Ecotap 260 MS"
	},
	{
		"name": "Ecotap 260MS"
	},
	{
		"name": "Ecotap 263MS"
	},
	{
		"name": "Ecotap 2834 DF"
	},
	{
		"name": "Ecotap 5300MF"
	},
	{
		"name": "Ecotap 531MS"
	},
	{
		"name": "Ecotap 532RS"
	},
	{
		"name": "Ecotap 621 MF"
	},
	{
		"name": "Ecotap 621BF"
	},
	{
		"name": "Ecotap 733 M/1"
	},
	{
		"name": "Ecotap 7331MF"
	},
	{
		"name": "Ecotap 7332MF"
	},
	{
		"name": "Ecotap 7336MF"
	},
	{
		"name": "Ecotap 733M/1"
	},
	{
		"name": "Ecotap 7361RF"
	},
	{
		"name": "Ecotap 7362RF"
	},
	{
		"name": "Ecotap 7363RF"
	},
	{
		"name": "Ecotap 7364RF"
	},
	{
		"name": "Ecotap 7365RF"
	},
	{
		"name": "Ecotap 7366RF"
	},
	{
		"name": "Ecotap 7367RF"
	},
	{
		"name": "Ecotap 7368RF"
	},
	{
		"name": "Ecotap 7369RF"
	},
	{
		"name": "Ecotap 7370RF"
	},
	{
		"name": "Ecotap 7371RF"
	},
	{
		"name": "Ecotap 7450H"
	},
	{
		"name": "Ecotap 7451H"
	},
	{
		"name": "Ecotap 7800 DF"
	},
	{
		"name": "Ecotap 7813 DF"
	},
	{
		"name": "Ecotap 8600MF"
	}
]